pokemontcgsdk/__init__.py
pokemontcgsdk/ability.py
pokemontcgsdk/ancienttrait.py
pokemontcgsdk/attack.py
pokemontcgsdk/card.py
pokemontcgsdk/cardimage.py
pokemontcgsdk/cardmarket.py
pokemontcgsdk/config.py
pokemontcgsdk/legality.py
pokemontcgsdk/querybuilder.py
pokemontcgsdk/rarity.py
pokemontcgsdk/resistance.py
pokemontcgsdk/restclient.py
pokemontcgsdk/set.py
pokemontcgsdk/setimage.py
pokemontcgsdk/subtype.py
pokemontcgsdk/supertype.py
pokemontcgsdk/tcgplayer.py
pokemontcgsdk/type.py
pokemontcgsdk/weakness.py
tests/__init__.py
tests/test_card.py
tests/test_config.py
tests/test_pokemontcgexception.py
tests/test_set.py
tests/test_subtype.py
tests/test_supertype.py
tests/test_type.py
pokemontcgsdk-3.4.0.dist-info/LICENSE.txt
pokemontcgsdk-3.4.0.dist-info/METADATA
pokemontcgsdk-3.4.0.dist-info/WHEEL
pokemontcgsdk-3.4.0.dist-info/entry_points.txt
pokemontcgsdk-3.4.0.dist-info/top_level.txt
pokemontcgsdk-3.4.0.dist-info/RECORD
